README.md
setup.cfg
setup.py
fitfeats/__init__.py
fitfeats/version.py
fitfeats/base/__init__.py
fitfeats/base/_base.py
fitfeats/datasets/__init__.py
fitfeats/datasets/fake_dataset.py
fitfeats/feature_engineering/__init__.py
fitfeats/feature_engineering/_feature_polynomials.py
fitfeats/feature_optimization/__init__.py
fitfeats/feature_optimization/_feature_optimizer.py
fitfeats/feature_selection/__init__.py
fitfeats/feature_selection/association_methods/__init__.py
fitfeats/feature_selection/association_methods/_classification.py
fitfeats/feature_selection/association_methods/_regression.py
fitfeats/feature_selection/mrmr/__init__.py
fitfeats/feature_selection/mrmr/_backward.py
fitfeats/feature_selection/mrmr/_base.py
fitfeats/feature_selection/mrmr/_forward.py
fitfeats/feature_selection/wrappers/__init__.py
fitfeats/feature_selection/wrappers/_backward.py
fitfeats/feature_selection/wrappers/_base.py
fitfeats/feature_selection/wrappers/_forward.py
fitfeats/metrics/__init__.py
fitfeats/metrics/_classification.py
fitfeats/metrics/_regression.py
fitfeats/utils/exceptions_messages.py
fitfeatures.egg-info/PKG-INFO
fitfeatures.egg-info/SOURCES.txt
fitfeatures.egg-info/dependency_links.txt
fitfeatures.egg-info/requires.txt
fitfeatures.egg-info/top_level.txt