Metadata-Version: 2.1
Name: fitfeatures
Version: 0.0.5
Summary: Python Feature Selection & Optimization library
Home-page: https://github.com/diogomatoschaves/fitfeatures
Author: Diogo Matos Chaves
Author-email: di.matoschaves@gmail.com
License: MIT license
Keywords: feature selection,feature optimization,machine learning,genetic algorithms,optimization
Platform: UNKNOWN
Classifier: Programming Language :: Python :: 3
Classifier: License :: OSI Approved :: MIT License
Classifier: Operating System :: OS Independent
Requires-Python: >=3.8
